{
  "Note": [
    {
      "id": 1,
      "title": "欢迎使用个人实用工具",
      "content": "这是您的第一条笔记，快来记录些什么吧！",
      "created_at": "2026-07-03T18:49:21.501411+00:00",
      "updated_at": "2026-07-03T18:49:21.501411+00:00"
    },
    {
      "id": 2,
      "title": "使用技巧",
      "content": "您可以在笔记中记录任何事情，包括备忘、想法、代码片段等。",
      "created_at": "2026-07-03T18:49:21.501411+00:00",
      "updated_at": "2026-07-03T18:49:21.501411+00:00"
    }
  ],
  "Todo": [
    {
      "id": 2,
      "title": "生成一个强密码",
      "completed": false,
      "created_at": "2026-07-03T18:49:21.502810+00:00"
    },
    {
      "id": 3,
      "title": "尝试二维码生成",
      "completed": false,
      "created_at": "2026-07-03T18:49:21.502810+00:00"
    },
    {
      "id": 4,
      "title": "查询本机 IP",
      "completed": false,
      "created_at": "2026-07-03T18:49:21.502810+00:00"
    },
    {
      "id": 1,
      "title": "体验笔记功能",
      "completed": true,
      "created_at": "2026-07-03T18:49:21.502810+00:00"
    }
  ],
  "GeneratedPassword": [
    {
      "id": 1,
      "password": "aB3#kL9@mN7&",
      "length": 16,
      "has_upper": true,
      "has_lower": true,
      "has_digits": true,
      "has_symbols": true,
      "created_at": "2026-07-03T18:49:21.502810+00:00"
    },
    {
      "id": 2,
      "password": "MyStr0ng!Pass",
      "length": 14,
      "has_upper": true,
      "has_lower": true,
      "has_digits": true,
      "has_symbols": true,
      "created_at": "2026-07-03T18:49:21.502810+00:00"
    }
  ],
  "SavedQRCode": [
    {
      "id": 1,
      "content": "https://github.com",
      "size": 200,
      "created_at": "2026-07-03T18:49:21.502810+00:00"
    },
    {
      "id": 2,
      "content": "https://www.python.org",
      "size": 300,
      "created_at": "2026-07-03T18:49:21.502810+00:00"
    }
  ],
  "IPLookupHistory": [
    {
      "id": 1,
      "query": "8.8.8.8",
      "ip": "8.8.8.8",
      "country": "United States",
      "region": "Virginia",
      "city": "Ashburn",
      "org": "Google LLC",
      "created_at": "2026-07-03T18:49:21.504236+00:00"
    },
    {
      "id": 2,
      "query": "github.com",
      "ip": "140.82.121.3",
      "country": "United States",
      "region": "California",
      "city": "San Francisco",
      "org": "GitHub, Inc.",
      "created_at": "2026-07-03T18:49:21.504236+00:00"
    }
  ],
  "ToolUsage": [
    {
      "id": 1,
      "tool": "notes",
      "action": "create",
      "detail": "创建了确认笔记",
      "created_at": "2026-07-03T18:49:21.504236+00:00"
    },
    {
      "id": 2,
      "tool": "todo",
      "action": "create",
      "detail": "添加了待办事项",
      "created_at": "2026-07-03T18:49:21.504236+00:00"
    },
    {
      "id": 3,
      "tool": "password",
      "action": "generate",
      "detail": "生成了密码长度:16",
      "created_at": "2026-07-03T18:49:21.504236+00:00"
    },
    {
      "id": 4,
      "tool": "qrcode",
      "action": "generate",
      "detail": "https://github.com",
      "created_at": "2026-07-03T18:49:21.504236+00:00"
    },
    {
      "id": 5,
      "tool": "ip",
      "action": "lookup",
      "detail": "8.8.8.8",
      "created_at": "2026-07-03T18:49:21.504236+00:00"
    }
  ]
}